{
    "/admin/desktop/js/app.js": "/admin/desktop/js/app.js?id=bf0ce3652b4d11481f62",
    "/admin/mobile/js/app.js": "/admin/mobile/js/app.js?id=3f26848e1e157e8be4a1",
    "/front/desktop/js/app.js": "/front/desktop/js/app.js?id=36ac17fe8fda02a62475",
    "/front/mobile/js/app.js": "/front/mobile/js/app.js?id=b31ec348615b709fc84d",
    "/front/mobile/css/app.css": "/front/mobile/css/app.css?id=03e0a7e76ea1e579064a",
    "/front/desktop/css/app.css": "/front/desktop/css/app.css?id=10b3c698639f8c23a959",
    "/admin/mobile/css/app.css": "/admin/mobile/css/app.css?id=0ef40dc2930857f6f7bd",
    "/admin/desktop/css/app.css": "/admin/desktop/css/app.css?id=60005f165d224cbda006"
}
